MANIFEST.in
README.md
requirements.txt
setup.cfg
setup.py
event_service_utils/__init__.py
event_service_utils/vekg_helper.py
event_service_utils.egg-info/PKG-INFO
event_service_utils.egg-info/SOURCES.txt
event_service_utils.egg-info/dependency_links.txt
event_service_utils.egg-info/not-zip-safe
event_service_utils.egg-info/requires.txt
event_service_utils.egg-info/top_level.txt
event_service_utils/event_generators_processors/__init__.py
event_service_utils/event_generators_processors/base.py
event_service_utils/event_generators_processors/img_based.py
event_service_utils/graph/__init__.py
event_service_utils/graph/base.py
event_service_utils/graph/engine.py
event_service_utils/graph/redis_graph.py
event_service_utils/img_serialization/__init__.py
event_service_utils/img_serialization/base.py
event_service_utils/img_serialization/cv2.py
event_service_utils/img_serialization/pil.py
event_service_utils/img_serialization/redis.py
event_service_utils/logging/__init__.py
event_service_utils/logging/decorators.py
event_service_utils/pub_sub/__init__.py
event_service_utils/pub_sub/base.py
event_service_utils/pub_sub/publishers.py
event_service_utils/pub_sub/subscribers.py
event_service_utils/schemas/__init__.py
event_service_utils/schemas/events.py
event_service_utils/schemas/internal_msgs.py
event_service_utils/services/__init__.py
event_service_utils/services/base.py
event_service_utils/services/event_driven.py
event_service_utils/services/registry.py
event_service_utils/services/tracer.py
event_service_utils/streams/__init__.py
event_service_utils/streams/base.py
event_service_utils/streams/redis.py
event_service_utils/tests/__init__.py
event_service_utils/tests/base_test_case.py
event_service_utils/tests/json_msg_helper.py
event_service_utils/tests/mocked_graphs.py
event_service_utils/tests/mocked_streams.py
event_service_utils/tracing/__init__.py
event_service_utils/tracing/jaeger.py