Metadata-Version: 1.0
Name: event-service-utils
Version: 1.7.2
Summary: Event service utils
Home-page: UNKNOWN
Author: Felipe Arruda Pontes
Author-email: felipe.arruda.pontes@insight-centre.org
License: Apache License, Version 2.0
Platform: UNKNOWN
